[
	{
		"url": "https://pan.baidu.com/s/1caaDNd",
		"title": "3、无锡泓石汇泉股权投资管理中心合伙协议.doc"
	},
	{
		"url": "https://pan.baidu.com/s/1caaDNe",
		"title": "20160702华晨宇火星演唱会（北京）.mp3"
	},
	{
		"url": "https://pan.baidu.com/s/1caaDNF",
		"title": "2016.9.15中秋早球活动资料"
	},
	{
		"url": "https://pan.baidu.com/s/1caaDNI",
		"title": "2016中国外文局公务员招考职位.xls"
	},
	{
		"url": "https://pan.baidu.com/s/1caaDNk",
		"title": "【2017】教育硕士333综合全程班"
	},
	{
		"url": "https://pan.baidu.com/s/1caaDNl",
		"title": "p27"
	},
	{
		"url": "https://pan.baidu.com/s/1caaDNW",
		"title": "MVI_8915.MP4"
	},
	{
		"url": "https://pan.baidu.com/s/1caaDNy",
		"title": "王誉颖2"
	},
	{
		"url": "https://pan.baidu.com/s/1caaDo2",
		"title": "P29MV103 SDA555XFL TDA9808 DPTV-MV 24C16.bin"
	},
	{
		"url": "https://pan.baidu.com/s/1caaDo4",
		"title": "2016.6.9--汇安--赵春华"
	},
	{
		"url": "https://pan.baidu.com/s/1caaDo5",
		"title": "《民用建筑设计通则》图示---06SJ813.pdf"
	},
	{
		"url": "https://pan.baidu.com/s/1caaDoI",
		"title": "张家佳字体设计"
	},
	{
		"url": "https://pan.baidu.com/s/1caaDoj",
		"title": "三国法-杨帆"
	},
	{
		"url": "https://pan.baidu.com/s/1caaDoO",
		"title": "Navicat资料 _20160923110631.txt"
	},
	{
		"url": "https://pan.baidu.com/s/1caaDoR",
		"title": "IMG_20160801_064834.jpg"
	},
	{
		"url": "https://pan.baidu.com/s/1caaDoU",
		"title": "2013年度注册会计师（专业阶段考试）《财管》真题.doc"
	},
	{
		"url": "https://pan.baidu.com/s/1caaDoy",
		"title": "七年级英语上册 Unit4 Food and Restaurants  lesson 30 U4_L30_3_S001音频素材 冀教版.mp3"
	},
	{
		"url": "https://pan.baidu.com/s/1caaDoZ",
		"title": "廖慧平+林     广东省深圳市宝安区石岩街道办石岩镇打树林工业区宏利高一楼          13714396149   全册覆膜"
	},
	{
		"url": "https://pan.baidu.com/s/1caaDOA",
		"title": "C300_S6_1_shuang_sheng_4_2_nand_2g_v1.0_20160818.rar"
	},
	{
		"url": "https://pan.baidu.com/s/1caaDOC",
		"title": "2016-01-15 112847.jpg"
	},
	{
		"url": "https://pan.baidu.com/s/1caaDOD",
		"title": "160923 SPAO ALL RIGHT 2016FW Campaign with AOA.mp4"
	},
	{
		"url": "https://pan.baidu.com/s/1caaDOG",
		"title": "Screenshot_2016-07-27-20-00-35.png"
	},
	{
		"url": "https://pan.baidu.com/s/1caaDO6",
		"title": "IMG_20160619_224944.jpg"
	},
	{
		"url": "https://pan.baidu.com/s/1caaDOh",
		"title": "20160910精选"
	},
	{
		"url": "https://pan.baidu.com/s/1caaDOK",
		"title": "【4D环绕电弹极品】戴上耳机，掌声别停，我还能行.mp3"
	},
	{
		"url": "https://pan.baidu.com/s/1caaDOp",
		"title": "百凤朝南"
	},
	{
		"url": "https://pan.baidu.com/s/1caaDOS",
		"title": "2016-07-03 094601.jpg"
	},
	{
		"url": "https://pan.baidu.com/s/1caaDpa",
		"title": "DSC_3530.JPG"
	},
	{
		"url": "https://pan.baidu.com/s/1caaDp0",
		"title": "mmexport1471843643515.jpg"
	},
	{
		"url": "https://pan.baidu.com/s/1caaDpb",
		"title": "Navicat资料 _20160923110631.txt"
	},
	{
		"url": "https://pan.baidu.com/s/1caaDp4",
		"title": "libemgucv-windows-x64-gpu-2.4.2.1777.exe"
	},
	{
		"url": "https://pan.baidu.com/s/1caaDpG",
		"title": "王世贞《安南传》.pdf"
	},
	{
		"url": "https://pan.baidu.com/s/1caaDp7",
		"title": "2016-09-08 140339.jpg"
	},
	{
		"url": "https://pan.baidu.com/s/1caaDpO",
		"title": "付费购买-4月1.80威武暴风合击传奇版本.zip"
	},
	{
		"url": "https://pan.baidu.com/s/1caaDpS",
		"title": "DW"
	},
	{
		"url": "https://pan.baidu.com/s/1caaDpw",
		"title": "Autodesk 3ds Max Entertainment Creation Suite Standard 2016 (x64) X-FORCED.part5.rar"
	},
	{
		"url": "https://pan.baidu.com/s/1caaDPa",
		"title": "中考123全程导练·物理·人教·九年级上（全国通用版）.doc"
	},
	{
		"url": "https://pan.baidu.com/s/1caaDP0",
		"title": "FF32 FSXDD 蛛背历险.7z"
	},
	{
		"url": "https://pan.baidu.com/s/1caaDPB",
		"title": "马桶画面"
	},
	{
		"url": "https://pan.baidu.com/s/1caaDPc",
		"title": "microMsg.1434201779066.jpg"
	},
	{
		"url": "https://pan.baidu.com/s/1caaDP2",
		"title": "2015-06-21 213005.png"
	},
	{
		"url": "https://pan.baidu.com/s/1caaDPD",
		"title": "库卡机器人TCP自动校准.mp4"
	},
	{
		"url": "https://pan.baidu.com/s/1caaDP5",
		"title": "九天星简介（精简版）.docx"
	},
	{
		"url": "https://pan.baidu.com/s/1caaDPG",
		"title": "老九门45.mp4"
	},
	{
		"url": "https://pan.baidu.com/s/1caaDP6",
		"title": "Fifth Harmony - Worth It(剪辑).mp3"
	},
	{
		"url": "https://pan.baidu.com/s/1caaDPj",
		"title": "01-国学-4097首"
	},
	{
		"url": "https://pan.baidu.com/s/1caaDPl",
		"title": "F_shanxing"
	},
	{
		"url": "https://pan.baidu.com/s/1caaDPQ",
		"title": "2016-09-18 090106.jpg"
	},
	{
		"url": "https://pan.baidu.com/s/1caaDPR",
		"title": "吉林省白山市浑江区合兴后门英子石锅烤肉 张秀英收 15943906006"
	},
	{
		"url": "https://pan.baidu.com/s/1caaDPV",
		"title": "滩羊毛抱枕粉色和绿色"
	},
	{
		"url": "https://pan.baidu.com/s/1caaDPX",
		"title": "DSC_6269.JPG"
	},
	{
		"url": "https://pan.baidu.com/s/1caaDq0",
		"title": "2016-08-19 100824.jpg"
	},
	{
		"url": "https://pan.baidu.com/s/1caaDqC",
		"title": "乐队视频"
	},
	{
		"url": "https://pan.baidu.com/s/1caaDqj",
		"title": "重生之美妻名媛.rar"
	},
	{
		"url": "https://pan.baidu.com/s/1caaDqn",
		"title": "计算机二级"
	},
	{
		"url": "https://pan.baidu.com/s/1caaDqo",
		"title": "Adobe_Audition_3.0.7283.exe"
	},
	{
		"url": "https://pan.baidu.com/s/1caaDqO",
		"title": "刑法卷四"
	},
	{
		"url": "https://pan.baidu.com/s/1caaDqQ",
		"title": "1474292152604.mp4"
	},
	{
		"url": "https://pan.baidu.com/s/1caaDqr",
		"title": "我的资源"
	},
	{
		"url": "https://pan.baidu.com/s/1caaDqx",
		"title": "Divinity.Original.Sin.2.v1.0.0.16922.9Tr.rar"
	},
	{
		"url": "https://pan.baidu.com/s/1caaDqX",
		"title": "60313HA.png"
	},
	{
		"url": "https://pan.baidu.com/s/1caaDQA",
		"title": "TK2002016-YesIdo023.JPG"
	},
	{
		"url": "https://pan.baidu.com/s/1caaDQ0",
		"title": "hanfengle123"
	},
	{
		"url": "https://pan.baidu.com/s/1caaDQC",
		"title": "成片第三版.mov"
	},
	{
		"url": "https://pan.baidu.com/s/1caaDQ6",
		"title": "录取通知房屋证明.pdf"
	},
	{
		"url": "https://pan.baidu.com/s/1caaDQh",
		"title": "2016年赣州事业单位笔试考前重要资料.pdf"
	},
	{
		"url": "https://pan.baidu.com/s/1caaDQ7",
		"title": "2016-01-12 142503.jpg"
	},
	{
		"url": "https://pan.baidu.com/s/1caaDQk",
		"title": "2016-06-15 061715.jpg"
	},
	{
		"url": "https://pan.baidu.com/s/1caaDQM",
		"title": "AA86 展厅 展馆设计模型 生物展厅3DMAX.zip"
	},
	{
		"url": "https://pan.baidu.com/s/1caaDQo",
		"title": "专升本.zip"
	},
	{
		"url": "https://pan.baidu.com/s/1caaDQt",
		"title": "第2课 线性回归与Logistic。案例：电子商务业绩预测"
	},
	{
		"url": "https://pan.baidu.com/s/1caaDQW",
		"title": "《末世重建》by茶叶蛋.txt"
	},
	{
		"url": "https://pan.baidu.com/s/1caaDQY",
		"title": "JDDZ-1.1.5.apk"
	},
	{
		"url": "https://pan.baidu.com/s/1caaDrA",
		"title": "《申论》红领名师模块班（钟君）"
	},
	{
		"url": "https://pan.baidu.com/s/1caaDrc",
		"title": "60307HA.png"
	},
	{
		"url": "https://pan.baidu.com/s/1caaDr4",
		"title": "校园叛徒_20160923111805.txt"
	},
	{
		"url": "https://pan.baidu.com/s/1caaDrn",
		"title": "泰国游"
	},
	{
		"url": "https://pan.baidu.com/s/1caaDrN",
		"title": "唐曾磊老师教育角度解读《金刚经》第69讲.mp3"
	},
	{
		"url": "https://pan.baidu.com/s/1caaDrs",
		"title": "柯达皇家绒面3寸"
	},
	{
		"url": "https://pan.baidu.com/s/1caaDrV",
		"title": "160915-25988373001"
	},
	{
		"url": "https://pan.baidu.com/s/1caaDrz",
		"title": "云图.mp4"
	},
	{
		"url": "https://pan.baidu.com/s/1caaDrZ",
		"title": "IMG_20140619_142022.jpg"
	},
	{
		"url": "https://pan.baidu.com/s/1caaDRC",
		"title": "《炮灰男配的一百种死法》by汪三岁.txt"
	},
	{
		"url": "https://pan.baidu.com/s/1caaDR2",
		"title": "8月广丰提交WAYS"
	},
	{
		"url": "https://pan.baidu.com/s/1caaDRG",
		"title": "2016-04-22 220855.jpg"
	},
	{
		"url": "https://pan.baidu.com/s/1caaDR6",
		"title": "2015-08-13 190753.jpg"
	},
	{
		"url": "https://pan.baidu.com/s/1caaDRI",
		"title": "2016-08-19 234337.jpg"
	},
	{
		"url": "https://pan.baidu.com/s/1caaDRL",
		"title": "mmexport1446692708350.jpg"
	},
	{
		"url": "https://pan.baidu.com/s/1caaDRu",
		"title": "2016-09-10 192733.jpg"
	},
	{
		"url": "https://pan.baidu.com/s/1caaDRw",
		"title": "P006.jpg"
	},
	{
		"url": "https://pan.baidu.com/s/1caaDsA",
		"title": "淘宝km爱阿姝20160923"
	},
	{
		"url": "https://pan.baidu.com/s/1caaDs2",
		"title": "[TSKS][W][E016(720P)][KO_CN].mkv"
	},
	{
		"url": "https://pan.baidu.com/s/1caaDse",
		"title": "9高潮.mp3"
	},
	{
		"url": "https://pan.baidu.com/s/1caaDsE",
		"title": "02-able.wmv"
	},
	{
		"url": "https://pan.baidu.com/s/1caaDsF",
		"title": "【2016.3—2016.8.15】孟瑞&amp;王博文全部资源汇总"
	},
	{
		"url": "https://pan.baidu.com/s/1caaDsg",
		"title": "2016-07-22 163021.jpg"
	},
	{
		"url": "https://pan.baidu.com/s/1caaDsG",
		"title": "02-able.wmv"
	},
	{
		"url": "https://pan.baidu.com/s/1caaDsm",
		"title": "vs2015.ent_chs.iso"
	},
	{
		"url": "https://pan.baidu.com/s/1caaDso",
		"title": "材质问题商品表格.xlsx"
	},
	{
		"url": "https://pan.baidu.com/s/1caaDsq",
		"title": "NBA2K17.v1.0-Update1.Plus.15.Fixed.rar"
	}
]