[
	{
		"url": "https://pan.baidu.com/s/1caajBA",
		"title": "s1 04 Best Friend.avi"
	},
	{
		"url": "https://pan.baidu.com/s/1caajBc",
		"title": "新建文件夹"
	},
	{
		"url": "https://pan.baidu.com/s/1caajBd",
		"title": "3dsmax2013chinese64bit.zip"
	},
	{
		"url": "https://pan.baidu.com/s/1caajBE",
		"title": "IMG_0295.JPG"
	},
	{
		"url": "https://pan.baidu.com/s/1caajBf",
		"title": "注会复习思维导图"
	},
	{
		"url": "https://pan.baidu.com/s/1caajBK",
		"title": "2016-09-13 105428.png"
	},
	{
		"url": "https://pan.baidu.com/s/1caajBU",
		"title": "2016年公职类考试资料全套"
	},
	{
		"url": "https://pan.baidu.com/s/1caajBY",
		"title": "骨折治疗的AO原则第2版--高清书签版，方便阅读.pdf"
	},
	{
		"url": "https://pan.baidu.com/s/1caaj1F",
		"title": "使 T 行 Z.2016.HDTC.国语对白.mp4"
	},
	{
		"url": "https://pan.baidu.com/s/1caaj1k",
		"title": "100个QQ实用小技术技巧.zip"
	},
	{
		"url": "https://pan.baidu.com/s/1caaj1P",
		"title": "【SSK字幕组】Lip.Sync.Battle.S02E19.720p.HDTV.mkv"
	},
	{
		"url": "https://pan.baidu.com/s/1caaj1t",
		"title": "伟ling.jpg"
	},
	{
		"url": "https://pan.baidu.com/s/1caaj1u",
		"title": "2016-09-08 101013.jpg"
	},
	{
		"url": "https://pan.baidu.com/s/1caaj1v",
		"title": "0716.zip"
	},
	{
		"url": "https://pan.baidu.com/s/1caaj1x",
		"title": "2015-11-23 152729.jpg"
	},
	{
		"url": "https://pan.baidu.com/s/1caaj1y",
		"title": "诗辰志在成功09：美乐家经营三大重点工作：倍增顾客.mp3"
	},
	{
		"url": "https://pan.baidu.com/s/1caaj1z",
		"title": "SGServer.rar"
	},
	{
		"url": "https://pan.baidu.com/s/1caajcg",
		"title": "2016-04-13 193642.jpg"
	},
	{
		"url": "https://pan.baidu.com/s/1caajcN",
		"title": "任意依恋"
	},
	{
		"url": "https://pan.baidu.com/s/1caajcp",
		"title": "[Kate_Fox]_Watching_the_English_the_Hidden_Rules_(BookZZ.org).pdf"
	},
	{
		"url": "https://pan.baidu.com/s/1caajcs",
		"title": "2016年3月份国内国际时事政治热点汇总.doc"
	},
	{
		"url": "https://pan.baidu.com/s/1caajCB",
		"title": "Heart"
	},
	{
		"url": "https://pan.baidu.com/s/1caajC6",
		"title": "Train.To.Busan.2016.HDRip.H264.AAC-Unknown.mp4"
	},
	{
		"url": "https://pan.baidu.com/s/1caajCH",
		"title": "319"
	},
	{
		"url": "https://pan.baidu.com/s/1caajCj",
		"title": "2016-05-06 121811.png"
	},
	{
		"url": "https://pan.baidu.com/s/1caajCK",
		"title": "釜山行2016"
	},
	{
		"url": "https://pan.baidu.com/s/1caaj2a",
		"title": "【微信公众号dyjia888最新电影首发】.mp4"
	},
	{
		"url": "https://pan.baidu.com/s/1caaj20",
		"title": "2059-祝遂之篆书技法与创作"
	},
	{
		"url": "https://pan.baidu.com/s/1caaj2C",
		"title": "谢安琪 - 钟无艳.ape"
	},
	{
		"url": "https://pan.baidu.com/s/1caaj22",
		"title": "店铺停车位_clip.mp4"
	},
	{
		"url": "https://pan.baidu.com/s/1caaj2E",
		"title": "ug安装包各个版本的安装包"
	},
	{
		"url": "https://pan.baidu.com/s/1caaj2f",
		"title": "水力学"
	},
	{
		"url": "https://pan.baidu.com/s/1caaj25",
		"title": "（2）20年真题+10年真题&amp;标准答案（30年）.zip"
	},
	{
		"url": "https://pan.baidu.com/s/1caaj2l",
		"title": "REC20160913190223.mp3"
	},
	{
		"url": "https://pan.baidu.com/s/1caaj2M",
		"title": "DNF_Client.zip"
	},
	{
		"url": "https://pan.baidu.com/s/1caaj2p",
		"title": "07.mkv"
	},
	{
		"url": "https://pan.baidu.com/s/1caaj2X",
		"title": "[小津安二郎的艺术][1].(日)佐藤忠男(2).pdf"
	},
	{
		"url": "https://pan.baidu.com/s/1caaj2z",
		"title": "DSC01178.JPG"
	},
	{
		"url": "https://pan.baidu.com/s/1caajd1",
		"title": "物语系列"
	},
	{
		"url": "https://pan.baidu.com/s/1caajd2",
		"title": "黑白-02.jpg"
	},
	{
		"url": "https://pan.baidu.com/s/1caajdd",
		"title": "瑞贝恩有机zxx.pdf"
	},
	{
		"url": "https://pan.baidu.com/s/1caajdK",
		"title": "呵护产品知识培训PPT.ppt"
	},
	{
		"url": "https://pan.baidu.com/s/1caajdl",
		"title": "徐立华德福备考全套（高清）"
	},
	{
		"url": "https://pan.baidu.com/s/1caajdp",
		"title": "IMG_7635.JPG"
	},
	{
		"url": "https://pan.baidu.com/s/1caajdS",
		"title": "玻璃芦苇"
	},
	{
		"url": "https://pan.baidu.com/s/1caajdw",
		"title": "v3.更多精彩关注微信公众号：哎生活vs爱生活.mp4"
	},
	{
		"url": "https://pan.baidu.com/s/1caajD3",
		"title": "数学"
	},
	{
		"url": "https://pan.baidu.com/s/1caajDK",
		"title": "2016-09-11 184248.jpg"
	},
	{
		"url": "https://pan.baidu.com/s/1caajDr",
		"title": "photoshopCS6软件+正版序列号 永久使用.zip"
	},
	{
		"url": "https://pan.baidu.com/s/1caajDT",
		"title": "视频集合.zip"
	},
	{
		"url": "https://pan.baidu.com/s/1caajDU",
		"title": "【音频+讲义】2016年众合卷四突破班六大名师-终极预测押题"
	},
	{
		"url": "https://pan.baidu.com/s/1caajDz",
		"title": "2001-3002.doc"
	},
	{
		"url": "https://pan.baidu.com/s/1caaj33",
		"title": "美队3.mkv"
	},
	{
		"url": "https://pan.baidu.com/s/1caaj3e",
		"title": "牛津树音频"
	},
	{
		"url": "https://pan.baidu.com/s/1caaj34",
		"title": "2013-11-15 211738.jpg"
	},
	{
		"url": "https://pan.baidu.com/s/1caaj36",
		"title": "EP44.mp4"
	},
	{
		"url": "https://pan.baidu.com/s/1caaj3l",
		"title": "9.zip"
	},
	{
		"url": "https://pan.baidu.com/s/1caaj3M",
		"title": "nhxg.mkv"
	},
	{
		"url": "https://pan.baidu.com/s/1caaj3O",
		"title": "DBC_2000-v6.8.zip"
	},
	{
		"url": "https://pan.baidu.com/s/1caaj3s",
		"title": "qbzj.mkv"
	},
	{
		"url": "https://pan.baidu.com/s/1caaj3S",
		"title": "Linux基础命令.pdf"
	},
	{
		"url": "https://pan.baidu.com/s/1caaj3t",
		"title": "9.12 天域"
	},
	{
		"url": "https://pan.baidu.com/s/1caaj3x",
		"title": "2.天问：秘密团队理念.m4a"
	},
	{
		"url": "https://pan.baidu.com/s/1caaj3Y",
		"title": "IMG_20160804_181414.jpg"
	},
	{
		"url": "https://pan.baidu.com/s/1caaj3Z",
		"title": "VID_20160909_203614.zip"
	},
	{
		"url": "https://pan.baidu.com/s/1caajee",
		"title": "S60829-100006.jpg"
	},
	{
		"url": "https://pan.baidu.com/s/1caajeg",
		"title": "Dasein素材"
	},
	{
		"url": "https://pan.baidu.com/s/1caaje6",
		"title": "2016 昭昭医考 第3天 串讲内容.pdf"
	},
	{
		"url": "https://pan.baidu.com/s/1caajeh",
		"title": "S03 微博@赵玮玮玮"
	},
	{
		"url": "https://pan.baidu.com/s/1caajel",
		"title": "9.3.mp4"
	},
	{
		"url": "https://pan.baidu.com/s/1caajE0",
		"title": "B612_20160912_121815.jpg"
	},
	{
		"url": "https://pan.baidu.com/s/1caajE3",
		"title": "37.釜 山 行"
	},
	{
		"url": "https://pan.baidu.com/s/1caajEe",
		"title": "Lifted_Music_ending_Demo.1.mp3"
	},
	{
		"url": "https://pan.baidu.com/s/1caajE8",
		"title": "言情.rar"
	},
	{
		"url": "https://pan.baidu.com/s/1caajEj",
		"title": "st_bd.mp4"
	},
	{
		"url": "https://pan.baidu.com/s/1caajEK",
		"title": "经管2016粗编.mp4"
	},
	{
		"url": "https://pan.baidu.com/s/1caajEN",
		"title": "神鬼吧架打.高清16集全（完结）-www.llduang.com"
	},
	{
		"url": "https://pan.baidu.com/s/1caajEs",
		"title": "20160910-018.mp3"
	},
	{
		"url": "https://pan.baidu.com/s/1caajEV",
		"title": "com.npc.sankuo.npc-520-release.apk"
	},
	{
		"url": "https://pan.baidu.com/s/1caajEw",
		"title": "Adobe Premiere Pro CC 2015.2.rar"
	},
	{
		"url": "https://pan.baidu.com/s/1caajEX",
		"title": "10寸冷裱照片2张，其余20张5寸照片"
	},
	{
		"url": "https://pan.baidu.com/s/1caaj4D",
		"title": "饼干圆圆02.mp3"
	},
	{
		"url": "https://pan.baidu.com/s/1caaj4e",
		"title": "《幸福的方法》"
	},
	{
		"url": "https://pan.baidu.com/s/1caaj4I",
		"title": "答案、课件、指南"
	},
	{
		"url": "https://pan.baidu.com/s/1caaj49",
		"title": "云画的月光7.mkv"
	},
	{
		"url": "https://pan.baidu.com/s/1caaj4M",
		"title": "2016年一级建造师《经济》模考练习卷（一）.pdf"
	},
	{
		"url": "https://pan.baidu.com/s/1caaj4O",
		"title": "2016-09-08 111534.jpg"
	},
	{
		"url": "https://pan.baidu.com/s/1caaj4t",
		"title": "Lol S6 WC A-copy0913.mp4"
	},
	{
		"url": "https://pan.baidu.com/s/1caaj4W",
		"title": "2016-08-17 140131.jpg"
	},
	{
		"url": "https://pan.baidu.com/s/1caaj4x",
		"title": "mmexport1461658006778.jpg"
	},
	{
		"url": "https://pan.baidu.com/s/1caaj4Y",
		"title": "使徒行者.2016.TS清晰中字首发-www.iidvd.com.mp4.torrent"
	},
	{
		"url": "https://pan.baidu.com/s/1caajfA",
		"title": "宠爱资源分享"
	},
	{
		"url": "https://pan.baidu.com/s/1caajfe",
		"title": "IB 完整升级测试.pdf"
	},
	{
		"url": "https://pan.baidu.com/s/1caajff",
		"title": "釜shanxing"
	},
	{
		"url": "https://pan.baidu.com/s/1caajfF",
		"title": "2016-08-12 114728.jpg"
	},
	{
		"url": "https://pan.baidu.com/s/1caajfj",
		"title": "We Make Cookies.pdf"
	},
	{
		"url": "https://pan.baidu.com/s/1caajfl",
		"title": "13流转粤剧 文化走亲VA0.mp4"
	},
	{
		"url": "https://pan.baidu.com/s/1caajfY",
		"title": "Adobe Animate CC 2015.1.1 (Flash Pro)"
	},
	{
		"url": "https://pan.baidu.com/s/1caajFB",
		"title": "十三罗汉"
	},
	{
		"url": "https://pan.baidu.com/s/1caajF1",
		"title": "2016-09-09 193342.jpg"
	}
]