[
	{
		"url": "https://pan.baidu.com/s/1caAfAJ",
		"title": "IMG_1806.MOV",
		"detail": "single_file_page"
	},
	{
		"url": "https://pan.baidu.com/s/1caAfAo",
		"title": "AUDITOIRE_XFL Launch",
		"detail": "multi_file"
	},
	{
		"url": "https://pan.baidu.com/s/1caAfAY",
		"title": "IMG_6335.JPG",
		"detail": "single_file_page"
	},
	{
		"url": "https://pan.baidu.com/s/1caAf00",
		"title": "语音合成助手_T恤衫大甩卖_夜色DJ背景音乐.mp3",
		"detail": "single_file_page"
	},
	{
		"url": "https://pan.baidu.com/s/1caAf01",
		"title": "_MG_3428.JPG",
		"detail": "single_file_page"
	},
	{
		"url": "https://pan.baidu.com/s/1caAf0d",
		"title": "口腔修复视频",
		"detail": "multi_file"
	},
	{
		"url": "https://pan.baidu.com/s/1caAf03",
		"title": "tfs2015_server_chs.iso",
		"detail": "single_file_page"
	},
	{
		"url": "https://pan.baidu.com/s/1caAf0M",
		"title": "AVSEQ04.DAT",
		"detail": "single_file_page"
	},
	{
		"url": "https://pan.baidu.com/s/1caAf0P",
		"title": "IMG_7279.mp4",
		"detail": "single_file_page"
	},
	{
		"url": "https://pan.baidu.com/s/1caAf0s",
		"title": "亿安科技作手井论3.pdf",
		"detail": "single_file_page"
	},
	{
		"url": "https://pan.baidu.com/s/1caAfbf",
		"title": "[①] 八雲紫と過ごす夜 (東方 Project).rar",
		"detail": "single_file_page"
	},
	{
		"url": "https://pan.baidu.com/s/1caAfb5",
		"title": "王者荣耀助手_1.0.0.524.apk",
		"detail": "single_file_page"
	},
	{
		"url": "https://pan.baidu.com/s/1caAfbg",
		"title": "4.30晚1.avi",
		"detail": "single_file_page"
	},
	{
		"url": "https://pan.baidu.com/s/1caAfbI",
		"title": "[马未都说收藏·杂项篇].pdf",
		"detail": "single_file_page"
	},
	{
		"url": "https://pan.baidu.com/s/1caAfbN",
		"title": "272.jpg",
		"detail": "single_file_page"
	},
	{
		"url": "https://pan.baidu.com/s/1caAfbO",
		"title": "卉卉",
		"detail": "multi_file"
	},
	{
		"url": "https://pan.baidu.com/s/1caAfbt",
		"title": "172A6084.jpg",
		"detail": "single_file_page"
	},
	{
		"url": "https://pan.baidu.com/s/1caAfbx",
		"title": "那年冬天风在吹",
		"detail": "multi_file"
	},
	{
		"url": "https://pan.baidu.com/s/1caAfbz",
		"title": "5.1上.avi",
		"detail": "single_file_page"
	},
	{
		"url": "https://pan.baidu.com/s/1caAfB8",
		"title": "2016.5.25 - 合肥宝库2.0",
		"detail": "multi_file"
	},
	{
		"url": "https://pan.baidu.com/s/1caAfBL",
		"title": "爱丽西亚王国MOD",
		"detail": "multi_file"
	},
	{
		"url": "https://pan.baidu.com/s/1caAfBo",
		"title": "￡龍族BT组￡【随时候命】【粤语】(dvd-rmvb)[全30集]",
		"detail": "multi_file"
	},
	{
		"url": "https://pan.baidu.com/s/1caAfBt",
		"title": "wmx❤zhz",
		"detail": "multi_file"
	},
	{
		"url": "https://pan.baidu.com/s/1caAf1A",
		"title": "08 Electric Guitar Tabata (feat. Coa.mp3",
		"detail": "single_file_page"
	},
	{
		"url": "https://pan.baidu.com/s/1caAf1L",
		"title": "[K-sub][Yuru Yuri Nachuyachumi!][OVA][720P][GB].mp4",
		"detail": "single_file_page"
	},
	{
		"url": "https://pan.baidu.com/s/1caAf1m",
		"title": "2015-01-26 211803.jpg",
		"detail": "single_file_page"
	},
	{
		"url": "https://pan.baidu.com/s/1caAf1q",
		"title": "会过去的-插先生.mp3",
		"detail": "single_file_page"
	},
	{
		"url": "https://pan.baidu.com/s/1caAf1U",
		"title": "1T3A4018.JPG",
		"detail": "single_file_page"
	},
	{
		"url": "https://pan.baidu.com/s/1caAfc4",
		"title": "[MAX1-M][场测-杭州-短信-CT]3.3-使用待测终端A给辅助终端B发送短信时出现一次发送短信时，提示发送失败，但辅助终端B收到4条重复该短信，如截图",
		"detail": "multi_file"
	},
	{
		"url": "https://pan.baidu.com/s/1caAfcH",
		"title": "《金包银》影展修改版.mov",
		"detail": "single_file_page"
	},
	{
		"url": "https://pan.baidu.com/s/1caAfc8",
		"title": "基于macd价格分段再探讨.pdf",
		"detail": "single_file_page"
	},
	{
		"url": "https://pan.baidu.com/s/1caAfc9",
		"title": "2016-04-20 055135.jpg",
		"detail": "single_file_page"
	},
	{
		"url": "https://pan.baidu.com/s/1caAfcK",
		"title": "圻哥一键免流（移动最新版）.apk",
		"detail": "single_file_page"
	},
	{
		"url": "https://pan.baidu.com/s/1caAfcl",
		"title": "IMG_0251.JPG",
		"detail": "single_file_page"
	},
	{
		"url": "https://pan.baidu.com/s/1caAfcp",
		"title": "IMGP1692.AVI",
		"detail": "single_file_page"
	},
	{
		"url": "https://pan.baidu.com/s/1caAfcT",
		"title": "ストリップバトルデイズ2",
		"detail": "multi_file"
	},
	{
		"url": "https://pan.baidu.com/s/1caAfCg",
		"title": "海洋学院与创客空间项目合作协议商榷书.docx",
		"detail": "single_file_page"
	},
	{
		"url": "https://pan.baidu.com/s/1caAfCl",
		"title": "cfqqtmtx324.rar",
		"detail": "single_file_page"
	},
	{
		"url": "https://pan.baidu.com/s/1caAfCr",
		"title": "《Boom Clap》舞蹈13级汇报演出.mov",
		"detail": "single_file_page"
	},
	{
		"url": "https://pan.baidu.com/s/1caAfCR",
		"title": "2O0A9863.JPG",
		"detail": "single_file_page"
	},
	{
		"url": "https://pan.baidu.com/s/1caAf24",
		"title": "《杭剧寻踪》影片最终版！！！.mov",
		"detail": "single_file_page"
	},
	{
		"url": "https://pan.baidu.com/s/1caAf2N",
		"title": "[S] 识骨寻踪 Bones 第1-12季 [www.xzhd365.com]",
		"detail": "multi_file"
	},
	{
		"url": "https://pan.baidu.com/s/1caAf2q",
		"title": "自拍4.mp4",
		"detail": "single_file_page"
	},
	{
		"url": "https://pan.baidu.com/s/1caAf2u",
		"title": "BEAST-good-luck.pdf",
		"detail": "single_file_page"
	},
	{
		"url": "https://pan.baidu.com/s/1caAf2X",
		"title": "2015年全国教师技能优秀作品",
		"detail": "multi_file"
	},
	{
		"url": "https://pan.baidu.com/s/1caAf2y",
		"title": "快乐大本营.mp4",
		"detail": "single_file_page"
	},
	{
		"url": "https://pan.baidu.com/s/1caAfdd",
		"title": "茅山后裔1传国宝玺(播音—青雪)(全69集){听书迷www.tingshumi.com}.zip",
		"detail": "multi_file"
	},
	{
		"url": "https://pan.baidu.com/s/1caAfdG",
		"title": "如何用加密播放器播放加密课件（必看）2.mp4",
		"detail": "multi_file"
	},
	{
		"url": "https://pan.baidu.com/s/1caAfdH",
		"title": "01",
		"detail": "multi_file"
	},
	{
		"url": "https://pan.baidu.com/s/1caAfdI",
		"title": "IMG_3305.JPG",
		"detail": "single_file_page"
	},
	{
		"url": "https://pan.baidu.com/s/1caAfdk",
		"title": "Cubase Elements 8.rar",
		"detail": "multi_file"
	},
	{
		"url": "https://pan.baidu.com/s/1caAfdt",
		"title": "IMG_0756 副本副本.jpg",
		"detail": "single_file_page"
	},
	{
		"url": "https://pan.baidu.com/s/1caAfdU",
		"title": "car1-1.jpg",
		"detail": "single_file_page"
	},
	{
		"url": "https://pan.baidu.com/s/1caAfdw",
		"title": "b13肘部原始点.avi",
		"detail": "single_file_page"
	},
	{
		"url": "https://pan.baidu.com/s/1caAfdy",
		"title": "西雅图不二情书.HD720p高清中字.mp4",
		"detail": "single_file_page"
	},
	{
		"url": "https://pan.baidu.com/s/1caAfDc",
		"title": "2016-05-25 194113.mov",
		"detail": "single_file_page"
	},
	{
		"url": "https://pan.baidu.com/s/1caAfDh",
		"title": "疑问.mp3",
		"detail": "single_file_page"
	},
	{
		"url": "https://pan.baidu.com/s/1caAfDQ",
		"title": "20110512019.mp4",
		"detail": "single_file_page"
	},
	{
		"url": "https://pan.baidu.com/s/1caAf30",
		"title": "SBD2微信794365478.rmvb",
		"detail": "single_file_page"
	},
	{
		"url": "https://pan.baidu.com/s/1caAf31",
		"title": "1T3A3335.JPG",
		"detail": "single_file_page"
	},
	{
		"url": "https://pan.baidu.com/s/1caAf3e",
		"title": "POI.501.HDTVrip.mp4",
		"detail": "single_file_page"
	},
	{
		"url": "https://pan.baidu.com/s/1caAf37",
		"title": "95年小妹被大汉按在床上猛力干.apk",
		"detail": "single_file_page"
	},
	{
		"url": "https://pan.baidu.com/s/1caAf3J",
		"title": "6寸",
		"detail": "multi_file"
	},
	{
		"url": "https://pan.baidu.com/s/1caAfe1",
		"title": "黄兵-销售副总裁.doc",
		"detail": "single_file_page"
	},
	{
		"url": "https://pan.baidu.com/s/1caAfeD",
		"title": "IIS+PHP外包服务器配置教程电脑板.exe",
		"detail": "multi_file"
	},
	{
		"url": "https://pan.baidu.com/s/1caAfe4",
		"title": "00003.MTS",
		"detail": "single_file_page"
	},
	{
		"url": "https://pan.baidu.com/s/1caAfef",
		"title": "160404 여성댄스팀 키씨(Kissy)(단비) - 우아하게_트와이스 (동대문 헬로 apm)(직캠 fancam).avi",
		"detail": "single_file_page"
	},
	{
		"url": "https://pan.baidu.com/s/1caAfe8",
		"title": "2016-05-25 192032.mov",
		"detail": "single_file_page"
	},
	{
		"url": "https://pan.baidu.com/s/1caAfeO",
		"title": "microMsg.1399733563873.jpg",
		"detail": "single_file_page"
	},
	{
		"url": "https://pan.baidu.com/s/1caAfeP",
		"title": "2014-11-29 153406.jpg",
		"detail": "single_file_page"
	},
	{
		"url": "https://pan.baidu.com/s/1caAfeR",
		"title": "冰雪奇缘",
		"detail": "multi_file"
	},
	{
		"url": "https://pan.baidu.com/s/1caAfeS",
		"title": "IMG_20140721_154626_0.jpg",
		"detail": "single_file_page"
	},
	{
		"url": "https://pan.baidu.com/s/1caAfE4",
		"title": "IMG_20160430_094142.jpg",
		"detail": "single_file_page"
	},
	{
		"url": "https://pan.baidu.com/s/1caAfEH",
		"title": "Tokyo Teleport - Tokyo Time Lapse _ Fast Motion.mp4.mp4",
		"detail": "single_file_page"
	},
	{
		"url": "https://pan.baidu.com/s/1caAfEk",
		"title": "经典普洱名词释义.pdf",
		"detail": "single_file_page"
	},
	{
		"url": "https://pan.baidu.com/s/1caAfEQ",
		"title": "DSCN2980.jpg",
		"detail": "single_file_page"
	},
	{
		"url": "https://pan.baidu.com/s/1caAfEZ",
		"title": "根哥",
		"detail": "multi_file"
	},
	{
		"url": "https://pan.baidu.com/s/1caAf48",
		"title": "答辩PPT.pptx",
		"detail": "single_file_page"
	},
	{
		"url": "https://pan.baidu.com/s/1caAf4J",
		"title": "45篇讲座讲话音频.rar",
		"detail": "single_file_page"
	},
	{
		"url": "https://pan.baidu.com/s/1caAf49",
		"title": "2016-03-01 124821.jpg",
		"detail": "single_file_page"
	},
	{
		"url": "https://pan.baidu.com/s/1caAf4V",
		"title": "2015锦囊妙“记”.pdf",
		"detail": "single_file_page"
	},
	{
		"url": "https://pan.baidu.com/s/1caAfff",
		"title": "剑10",
		"detail": "multi_file"
	},
	{
		"url": "https://pan.baidu.com/s/1caAff7",
		"title": "2015-12-11 122043(1).jpg",
		"detail": "single_file_page"
	},
	{
		"url": "https://pan.baidu.com/s/1caAffj",
		"title": "wifi杀手",
		"detail": "multi_file"
	},
	{
		"url": "https://pan.baidu.com/s/1caAffJ",
		"title": "IMG20150621135400.jpg",
		"detail": "single_file_page"
	},
	{
		"url": "https://pan.baidu.com/s/1caAffr",
		"title": "[Signal][第05集][韩语中字].rmvb",
		"detail": "single_file_page"
	},
	{
		"url": "https://pan.baidu.com/s/1caAffs",
		"title": "Taylor Swift - Wildest Dreams.mp3",
		"detail": "single_file_page"
	},
	{
		"url": "https://pan.baidu.com/s/1caAffu",
		"title": "2015-07-05 112816.jpg",
		"detail": "single_file_page"
	},
	{
		"url": "https://pan.baidu.com/s/1caAffy",
		"title": "2016-03-07 132827.jpg",
		"detail": "single_file_page"
	},
	{
		"url": "https://pan.baidu.com/s/1caAfFa",
		"title": "13.Hours.The.Secret.Soldiers.of.Benghazi.2016.1080p.WEB-DL.DD5.1.H264-RARBG-[rarbg.com].torrent",
		"detail": "single_file_page"
	},
	{
		"url": "https://pan.baidu.com/s/1caAfFE",
		"title": "3S8A9677.jpg",
		"detail": "single_file_page"
	},
	{
		"url": "https://pan.baidu.com/s/1caAfFG",
		"title": "3S8A9709.jpg",
		"detail": "single_file_page"
	},
	{
		"url": "https://pan.baidu.com/s/1caAfFJ",
		"title": "2016-05-11 095100.mov",
		"detail": "single_file_page"
	},
	{
		"url": "https://pan.baidu.com/s/1caAfFK",
		"title": "3S8A9954.jpg",
		"detail": "single_file_page"
	},
	{
		"url": "https://pan.baidu.com/s/1caAfFO",
		"title": "2016-05-09 182851.jpg",
		"detail": "single_file_page"
	},
	{
		"url": "https://pan.baidu.com/s/1caAfFq",
		"title": "Confused.wav",
		"detail": "single_file_page"
	},
	{
		"url": "https://pan.baidu.com/s/1caAfFr",
		"title": "2016-05-09 235021.jpg",
		"detail": "single_file_page"
	},
	{
		"url": "https://pan.baidu.com/s/1caAfFS",
		"title": "亡界之门.2016.HD720P.英语中字.mkv",
		"detail": "single_file_page"
	},
	{
		"url": "https://pan.baidu.com/s/1caAfFU",
		"title": "2016-05-15 165043.jpg",
		"detail": "single_file_page"
	},
	{
		"url": "https://pan.baidu.com/s/1caAfFV",
		"title": "Qomolangma-Title.ttf",
		"detail": "single_file_page"
	}
]