[
	{
		"url": "https://pan.baidu.com/s/1caAJlK",
		"title": "印制电路技术 教学课件 ppt 作者 金鸿陈森 主编 CH2 第二章 印制板用基板材料 2.rar",
		"detail": "single_file_page"
	},
	{
		"url": "https://pan.baidu.com/s/1caAJlL",
		"title": "2爱奇艺VIP版v12(推荐).apk",
		"detail": "single_file_page"
	},
	{
		"url": "https://pan.baidu.com/s/1caAJlM",
		"title": "精通.NET互操作.pdf",
		"detail": "single_file_page"
	},
	{
		"url": "https://pan.baidu.com/s/1caAJlo",
		"title": "2015-07-10 164826.jpg",
		"detail": "single_file_page"
	},
	{
		"url": "https://pan.baidu.com/s/1caAJlQ",
		"title": "P1020253.JPG",
		"detail": "single_file_page"
	},
	{
		"url": "https://pan.baidu.com/s/1caAJlS",
		"title": "2013年1月北京同步更新升级 (1).mp4",
		"detail": "single_file_page"
	},
	{
		"url": "https://pan.baidu.com/s/1caAJlt",
		"title": "P1020261.JPG",
		"detail": "single_file_page"
	},
	{
		"url": "https://pan.baidu.com/s/1caAJlu",
		"title": "1.txt",
		"detail": "single_file_page"
	},
	{
		"url": "https://pan.baidu.com/s/1caAJlv",
		"title": "2016-06-07 175424.jpg",
		"detail": "single_file_page"
	},
	{
		"url": "https://pan.baidu.com/s/1caAJlZ",
		"title": "2016-04-09 121137.jpg",
		"detail": "single_file_page"
	},
	{
		"url": "https://pan.baidu.com/s/1caAJLf",
		"title": "2016-06-06 123426.jpg",
		"detail": "single_file_page"
	},
	{
		"url": "https://pan.baidu.com/s/1caAJLg",
		"title": "小明老笨了.wav",
		"detail": "single_file_page"
	},
	{
		"url": "https://pan.baidu.com/s/1caAJLI",
		"title": "20160608 砚",
		"detail": "multi_file"
	},
	{
		"url": "https://pan.baidu.com/s/1caAJLL",
		"title": "Signed_fireball_2.17.605.2.zip",
		"detail": "single_file_page"
	},
	{
		"url": "https://pan.baidu.com/s/1caAJLM",
		"title": "2016-01-29 10.47.08.jpg",
		"detail": "single_file_page"
	},
	{
		"url": "https://pan.baidu.com/s/1caAJLw",
		"title": "2016-01-29 10.47.52.jpg",
		"detail": "single_file_page"
	},
	{
		"url": "https://pan.baidu.com/s/1caAJmd",
		"title": "jsp0059论坛BBS.rar",
		"detail": "multi_file"
	},
	{
		"url": "https://pan.baidu.com/s/1caAJme",
		"title": "04 前世情人.m4a",
		"detail": "single_file_page"
	},
	{
		"url": "https://pan.baidu.com/s/1caAJmf",
		"title": "愤怒的小鸟.国语高清版.mp4",
		"detail": "single_file_page"
	}
]