[
	{
		"url": "https://pan.baidu.com/s/1caaqhN",
		"title": "刘诗诗",
		"detail": "multi_file"
	},
	{
		"url": "https://pan.baidu.com/s/1caaqho",
		"title": "E08.mkv",
		"detail": "single_file_page"
	},
	{
		"url": "https://pan.baidu.com/s/1caaqhR",
		"title": "OFFice",
		"detail": "multi_file"
	},
	{
		"url": "https://pan.baidu.com/s/1caaqhT",
		"title": "备用源文件",
		"detail": "multi_file"
	},
	{
		"url": "https://pan.baidu.com/s/1caaqhz",
		"title": "马克.维尔赛斯小军鼓最新教程CD+书",
		"detail": "multi_file"
	},
	{
		"url": "https://pan.baidu.com/s/1caaqHA",
		"title": "IMG_5335.JPG",
		"detail": "single_file_page"
	},
	{
		"url": "https://pan.baidu.com/s/1caaqHc",
		"title": "6744道菜谱大全..chm",
		"detail": "multi_file"
	},
	{
		"url": "https://pan.baidu.com/s/1caaqH3",
		"title": "20140106_221501.jpg",
		"detail": "single_file_page"
	},
	{
		"url": "https://pan.baidu.com/s/1caaqH4",
		"title": "[W][E015(720P)][KO_CN].mkv",
		"detail": "single_file_page"
	},
	{
		"url": "https://pan.baidu.com/s/1caaqH6",
		"title": "数据库访问与数据库程序设计 项目式 教学课件 ppt 作者 陈承欢 单元3 从数据表中获取单一数据.rar",
		"detail": "single_file_page"
	},
	{
		"url": "https://pan.baidu.com/s/1caaqH9",
		"title": "NCRETEST_CrAck.zip",
		"detail": "single_file_page"
	},
	{
		"url": "https://pan.baidu.com/s/1caaqHO",
		"title": "2016-08-22 180712.png",
		"detail": "single_file_page"
	},
	{
		"url": "https://pan.baidu.com/s/1caaqHQ",
		"title": "蒲剧新《清风亭》变速伴奏5666.mp3",
		"detail": "single_file_page"
	},
	{
		"url": "https://pan.baidu.com/s/1caaq7K",
		"title": "mmexport1473942371107.jpg",
		"detail": "multi_file"
	},
	{
		"url": "https://pan.baidu.com/s/1caaq7n",
		"title": "明月守护者.mp4",
		"detail": "single_file_page"
	},
	{
		"url": "https://pan.baidu.com/s/1caaq7o",
		"title": "2017恋恋有词",
		"detail": "multi_file"
	},
	{
		"url": "https://pan.baidu.com/s/1caaq7s",
		"title": "08.mp4",
		"detail": "multi_file"
	},
	{
		"url": "https://pan.baidu.com/s/1caaq7w",
		"title": "IMG_20160915_101302.jpg",
		"detail": "single_file_page"
	},
	{
		"url": "https://pan.baidu.com/s/1caaqid",
		"title": "1-500UG建模视频",
		"detail": "multi_file"
	},
	{
		"url": "https://pan.baidu.com/s/1caaqi3",
		"title": "[TSKS][W][E016(720P)][KO_CN].mkv",
		"detail": "single_file_page"
	},
	{
		"url": "https://pan.baidu.com/s/1caaqii",
		"title": "晚婷",
		"detail": "multi_file"
	},
	{
		"url": "https://pan.baidu.com/s/1caaqio",
		"title": "04.jpg",
		"detail": "single_file_page"
	},
	{
		"url": "https://pan.baidu.com/s/1caaqiU",
		"title": "DSC02727.JPG",
		"detail": "single_file_page"
	},
	{
		"url": "https://pan.baidu.com/s/1caaqIf",
		"title": "_MG_1428.JPG",
		"detail": "single_file_page"
	},
	{
		"url": "https://pan.baidu.com/s/1caaqIG",
		"title": "IMG_20160223_193825.jpg",
		"detail": "single_file_page"
	},
	{
		"url": "https://pan.baidu.com/s/1caaqIK",
		"title": "2016-02-21 114758.jpg",
		"detail": "single_file_page"
	},
	{
		"url": "https://pan.baidu.com/s/1caaqIL",
		"title": "2016-05-16 223758.jpg",
		"detail": "single_file_page"
	},
	{
		"url": "https://pan.baidu.com/s/1caaqIm",
		"title": "DSC00689.JPG",
		"detail": "single_file_page"
	},
	{
		"url": "https://pan.baidu.com/s/1caaqIo",
		"title": "改进飞行高质感钢铁侠.zip",
		"detail": "single_file_page"
	},
	{
		"url": "https://pan.baidu.com/s/1caaqIZ",
		"title": "ご主人様はヤバい奴1+2【游叶】k.rar",
		"detail": "single_file_page"
	},
	{
		"url": "https://pan.baidu.com/s/1caaq84",
		"title": "釜山行中字",
		"detail": "multi_file"
	},
	{
		"url": "https://pan.baidu.com/s/1caaq89",
		"title": "文豪野犬",
		"detail": "multi_file"
	},
	{
		"url": "https://pan.baidu.com/s/1caaq8L",
		"title": "ZH2.mp4",
		"detail": "single_file_page"
	},
	{
		"url": "https://pan.baidu.com/s/1caaq8Q",
		"title": "2015-11-06 101815.jpg",
		"detail": "single_file_page"
	},
	{
		"url": "https://pan.baidu.com/s/1caaq8V",
		"title": "2012.06.21歹歹的调皮 (2).MOV",
		"detail": "single_file_page"
	},
	{
		"url": "https://pan.baidu.com/s/1caaq8Y",
		"title": "290.JPG",
		"detail": "single_file_page"
	},
	{
		"url": "https://pan.baidu.com/s/1caaq8Z",
		"title": "2016-08-13 215042.jpg",
		"detail": "single_file_page"
	},
	{
		"url": "https://pan.baidu.com/s/1caaqj0",
		"title": "高一十 梁嘉展 ityoul 摄影作品2",
		"detail": "multi_file"
	},
	{
		"url": "https://pan.baidu.com/s/1caaqjk",
		"title": "2016-08-20 162503.jpg",
		"detail": "single_file_page"
	},
	{
		"url": "https://pan.baidu.com/s/1caaqjK",
		"title": "2016-09-15 161729.jpg",
		"detail": "multi_file"
	},
	{
		"url": "https://pan.baidu.com/s/1caaqjY",
		"title": "打印",
		"detail": "multi_file"
	},
	{
		"url": "https://pan.baidu.com/s/1caaqJ1",
		"title": "遗愿清单.rmvb",
		"detail": "single_file_page"
	},
	{
		"url": "https://pan.baidu.com/s/1caaqJd",
		"title": "AE2015.rar",
		"detail": "single_file_page"
	},
	{
		"url": "https://pan.baidu.com/s/1caaqJg",
		"title": "2015-11-14 225302.jpg",
		"detail": "single_file_page"
	},
	{
		"url": "https://pan.baidu.com/s/1caaqJJ",
		"title": "2016-09-07 093457.jpg",
		"detail": "single_file_page"
	},
	{
		"url": "https://pan.baidu.com/s/1caaqJl",
		"title": "2015-04-16 121310.jpg",
		"detail": "single_file_page"
	},
	{
		"url": "https://pan.baidu.com/s/1caaqJL",
		"title": "IMG_20160827_161237.jpg",
		"detail": "single_file_page"
	},
	{
		"url": "https://pan.baidu.com/s/1caaqJM",
		"title": "1447982157761.jpeg",
		"detail": "single_file_page"
	},
	{
		"url": "https://pan.baidu.com/s/1caaqJn",
		"title": "西瓜家@普吉岛攻略和地图.zip",
		"detail": "single_file_page"
	},
	{
		"url": "https://pan.baidu.com/s/1caaqJN",
		"title": "火影忍者100多个忍术2.rar",
		"detail": "single_file_page"
	},
	{
		"url": "https://pan.baidu.com/s/1caaqJp",
		"title": "IMG_20151209_220008.jpg",
		"detail": "single_file_page"
	},
	{
		"url": "https://pan.baidu.com/s/1caaqJr",
		"title": "2016.9.11月猫 张杰",
		"detail": "multi_file"
	},
	{
		"url": "https://pan.baidu.com/s/1caaqJY",
		"title": "手机版《走出军营放飞梦想》73分队老兵退伍视频.mp4",
		"detail": "single_file_page"
	},
	{
		"url": "https://pan.baidu.com/s/1caaqJz",
		"title": "2016-06-02 233432.jpg",
		"detail": "single_file_page"
	},
	{
		"url": "https://pan.baidu.com/s/1caaq9c",
		"title": "241 开胸术-茅继良.MPG",
		"detail": "single_file_page"
	},
	{
		"url": "https://pan.baidu.com/s/1caaq9D",
		"title": "《FS行》微博@宿舍电影",
		"detail": "multi_file"
	},
	{
		"url": "https://pan.baidu.com/s/1caaq9E",
		"title": "开场图.JPG",
		"detail": "single_file_page"
	},
	{
		"url": "https://pan.baidu.com/s/1caaq9g",
		"title": "我的资源",
		"detail": "multi_file"
	},
	{
		"url": "https://pan.baidu.com/s/1caaq9j",
		"title": "Kingsglaive",
		"detail": "multi_file"
	},
	{
		"url": "https://pan.baidu.com/s/1caaq9M",
		"title": "2015-09-27 092538.jpg",
		"detail": "single_file_page"
	},
	{
		"url": "https://pan.baidu.com/s/1caaq9o",
		"title": "大陆6-7岁彩虹版12集",
		"detail": "multi_file"
	},
	{
		"url": "https://pan.baidu.com/s/1caaq9r",
		"title": "主观题",
		"detail": "multi_file"
	},
	{
		"url": "https://pan.baidu.com/s/1caaq9v",
		"title": "MI3TD",
		"detail": "multi_file"
	},
	{
		"url": "https://pan.baidu.com/s/1caaqkb",
		"title": "蒋勳 - 细说红楼梦 - 第52回下.mp3",
		"detail": "single_file_page"
	},
	{
		"url": "https://pan.baidu.com/s/1caaqk3",
		"title": "爱剪辑-录人簿-八世之约.mp4",
		"detail": "single_file_page"
	},
	{
		"url": "https://pan.baidu.com/s/1caaqkE",
		"title": "釜山行_bd.mp4",
		"detail": "single_file_page"
	},
	{
		"url": "https://pan.baidu.com/s/1caaqk4",
		"title": "01. 너를 위해.mp3",
		"detail": "single_file_page"
	},
	{
		"url": "https://pan.baidu.com/s/1caaqk7",
		"title": "子骞老师第一次教练直播.MP4",
		"detail": "single_file_page"
	},
	{
		"url": "https://pan.baidu.com/s/1caaqkj",
		"title": "20153211016.zip",
		"detail": "single_file_page"
	},
	{
		"url": "https://pan.baidu.com/s/1caaqkk",
		"title": "E03.390影视.rmvb",
		"detail": "single_file_page"
	},
	{
		"url": "https://pan.baidu.com/s/1caaqkM",
		"title": "龙儿求生.rar",
		"detail": "single_file_page"
	},
	{
		"url": "https://pan.baidu.com/s/1caaqkt",
		"title": "2016.TC720P.英语中字.mp4",
		"detail": "single_file_page"
	},
	{
		"url": "https://pan.baidu.com/s/1caaqkX",
		"title": "【控制(控城计)(空城计)】【高清1280版HD-RMVB.国语中字】【2013吴彦祖、姚晨、任达华动作大片】",
		"detail": "multi_file"
	},
	{
		"url": "https://pan.baidu.com/s/1caaqK3",
		"title": "2016-03-06 165622.jpg",
		"detail": "single_file_page"
	},
	{
		"url": "https://pan.baidu.com/s/1caaqKE",
		"title": "48.mp4",
		"detail": "single_file_page"
	},
	{
		"url": "https://pan.baidu.com/s/1caaqKf",
		"title": "社会实践感想个人版.zip",
		"detail": "single_file_page"
	},
	{
		"url": "https://pan.baidu.com/s/1caaqK5",
		"title": "2016-02-07 104501.jpg",
		"detail": "single_file_page"
	},
	{
		"url": "https://pan.baidu.com/s/1caaqK8",
		"title": "刘亦菲  王铮亮 - 还在这里 (《致青春2》电影的主题曲).mp3",
		"detail": "single_file_page"
	},
	{
		"url": "https://pan.baidu.com/s/1caaqKo",
		"title": "追逐星星的孩子.mp4",
		"detail": "single_file_page"
	},
	{
		"url": "https://pan.baidu.com/s/1caaqKZ",
		"title": "〖爱鬼哥破解〗瓦力抢红包（_VIP_）v2.9.7花花新版.apk",
		"detail": "single_file_page"
	},
	{
		"url": "https://pan.baidu.com/s/1caaql0",
		"title": "[阳光电影www.ygdy8.com].釜山行.HD.720p.韩语中字.rmvb",
		"detail": "single_file_page"
	},
	{
		"url": "https://pan.baidu.com/s/1caaql4",
		"title": "美3中英双字.mp4",
		"detail": "single_file_page"
	},
	{
		"url": "https://pan.baidu.com/s/1caaql8",
		"title": "IMG_20151226_183501.jpg",
		"detail": "single_file_page"
	},
	{
		"url": "https://pan.baidu.com/s/1caaqlN",
		"title": "IMG_1049.jpg",
		"detail": "single_file_page"
	},
	{
		"url": "https://pan.baidu.com/s/1caaqlo",
		"title": "徐磊语法基础写作班",
		"detail": "multi_file"
	},
	{
		"url": "https://pan.baidu.com/s/1caaqlO",
		"title": "追书神器破解版1.apk",
		"detail": "single_file_page"
	},
	{
		"url": "https://pan.baidu.com/s/1caaqlx",
		"title": "张博士医考视频泌尿系统9.flv",
		"detail": "single_file_page"
	},
	{
		"url": "https://pan.baidu.com/s/1caaqLa",
		"title": "2016-02-22 133325.jpg",
		"detail": "single_file_page"
	},
	{
		"url": "https://pan.baidu.com/s/1caaqL0",
		"title": "危城(1)",
		"detail": "multi_file"
	},
	{
		"url": "https://pan.baidu.com/s/1caaqL1",
		"title": "2016-08-28 131355_副本.jpg",
		"detail": "single_file_page"
	},
	{
		"url": "https://pan.baidu.com/s/1caaqL4",
		"title": "729",
		"detail": "multi_file"
	},
	{
		"url": "https://pan.baidu.com/s/1caaqLf",
		"title": "2016-07-01 213754.jpg",
		"detail": "single_file_page"
	},
	{
		"url": "https://pan.baidu.com/s/1caaqLF",
		"title": "一个人的北京-水瓶男.mp3",
		"detail": "single_file_page"
	},
	{
		"url": "https://pan.baidu.com/s/1caaqLg",
		"title": "食品微生物 教学课件 ppt 作者 朱乐敏 主编 周凤霞 主审 第六章 微生物引起的食品污染与腐败变质.rar",
		"detail": "single_file_page"
	},
	{
		"url": "https://pan.baidu.com/s/1caaqLR",
		"title": "2015-09-03 030108.jpg",
		"detail": "single_file_page"
	},
	{
		"url": "https://pan.baidu.com/s/1caaqLT",
		"title": "IMG_20150320_175235.jpg",
		"detail": "single_file_page"
	},
	{
		"url": "https://pan.baidu.com/s/1caaqLz",
		"title": "_52A1822.JPG",
		"detail": "single_file_page"
	},
	{
		"url": "https://pan.baidu.com/s/1caaqma",
		"title": "f7b425434c3ecf4f982b6ba15362d539_75706300.apk",
		"detail": "single_file_page"
	},
	{
		"url": "https://pan.baidu.com/s/1caaqm1",
		"title": "[TSKS][W][E015(720P)][KO_CN].mkv",
		"detail": "single_file_page"
	},
	{
		"url": "https://pan.baidu.com/s/1caaqmd",
		"title": "哥哥铃声",
		"detail": "multi_file"
	}
]