[
	{
		"url": "https://pan.baidu.com/s/1caasEr",
		"title": "S60226-075331.jpg",
		"detail": "single_file_page"
	},
	{
		"url": "https://pan.baidu.com/s/1caasER",
		"title": "[SOFCJ-Raws] Boruto - Naruto the Movie (BDRip 1280x688 x264 10bit FLACx2).mkv",
		"detail": "single_file_page"
	},
	{
		"url": "https://pan.baidu.com/s/1caasEV",
		"title": "20160915中秋联欢会.zip",
		"detail": "single_file_page"
	},
	{
		"url": "https://pan.baidu.com/s/1caasEX",
		"title": "2016-08-02 144123.jpg",
		"detail": "single_file_page"
	},
	{
		"url": "https://pan.baidu.com/s/1caas42",
		"title": "2016-06-14 194848.jpg",
		"detail": "single_file_page"
	},
	{
		"url": "https://pan.baidu.com/s/1caas4d",
		"title": "OST Part.4",
		"detail": "multi_file"
	},
	{
		"url": "https://pan.baidu.com/s/1caas4g",
		"title": "2015-09-05 075647.jpg",
		"detail": "single_file_page"
	},
	{
		"url": "https://pan.baidu.com/s/1caas4L",
		"title": "亿利生态－20151229.mp4",
		"detail": "single_file_page"
	},
	{
		"url": "https://pan.baidu.com/s/1caas4Y",
		"title": "IMG_20160901_173647.jpg",
		"detail": "single_file_page"
	},
	{
		"url": "https://pan.baidu.com/s/1caasfA",
		"title": "开心消消乐 v1.5破解版_ccplay.com.cn.apk",
		"detail": "single_file_page"
	},
	{
		"url": "https://pan.baidu.com/s/1caasfb",
		"title": "mmexport1457100567869.jpg",
		"detail": "single_file_page"
	},
	{
		"url": "https://pan.baidu.com/s/1caasfc",
		"title": "海洋之歌.mp4",
		"detail": "single_file_page"
	},
	{
		"url": "https://pan.baidu.com/s/1caasfD",
		"title": "晾衣架代理价格.pdf",
		"detail": "single_file_page"
	},
	{
		"url": "https://pan.baidu.com/s/1caasff",
		"title": "海报0914",
		"detail": "multi_file"
	},
	{
		"url": "https://pan.baidu.com/s/1caasfF",
		"title": "DSC_9625.JPG",
		"detail": "single_file_page"
	},
	{
		"url": "https://pan.baidu.com/s/1caasf5",
		"title": "2016-08-26 174503.jpg",
		"detail": "single_file_page"
	},
	{
		"url": "https://pan.baidu.com/s/1caasfH",
		"title": "2016-08-24 100052.jpg",
		"detail": "single_file_page"
	},
	{
		"url": "https://pan.baidu.com/s/1caasfw",
		"title": "microMsg.1367303623380.jpg",
		"detail": "single_file_page"
	},
	{
		"url": "https://pan.baidu.com/s/1caasFg",
		"title": "2014迎新环校跑",
		"detail": "multi_file"
	},
	{
		"url": "https://pan.baidu.com/s/1caasFH",
		"title": "65-广电局片头.wmv",
		"detail": "single_file_page"
	},
	{
		"url": "https://pan.baidu.com/s/1caasF9",
		"title": "MYXJ_20150505201650_save.jpg",
		"detail": "single_file_page"
	},
	{
		"url": "https://pan.baidu.com/s/1caasFn",
		"title": "-6ee2ac8b94dccf30.jpg",
		"detail": "single_file_page"
	},
	{
		"url": "https://pan.baidu.com/s/1caasFo",
		"title": "Allen&amp;Peach-707.jpg",
		"detail": "single_file_page"
	},
	{
		"url": "https://pan.baidu.com/s/1caasFX",
		"title": "2015-10-04 135034.jpg",
		"detail": "single_file_page"
	},
	{
		"url": "https://pan.baidu.com/s/1caasFY",
		"title": "二建",
		"detail": "multi_file"
	},
	{
		"url": "https://pan.baidu.com/s/1caas5a",
		"title": "Second Moon - Love in the Moonlight OST Special BGM",
		"detail": "multi_file"
	},
	{
		"url": "https://pan.baidu.com/s/1caas5b",
		"title": "还书妈妈义工指导与金老师讲座（蓝字的补充）.docx",
		"detail": "single_file_page"
	},
	{
		"url": "https://pan.baidu.com/s/1caas59",
		"title": "那件疯狂的小事叫爱情.2016.HD720P.mp4",
		"detail": "single_file_page"
	},
	{
		"url": "https://pan.baidu.com/s/1caas5n",
		"title": "Allen&amp;Peach-100.jpg",
		"detail": "single_file_page"
	},
	{
		"url": "https://pan.baidu.com/s/1caas5p",
		"title": "2016-08-27 120612.jpg",
		"detail": "single_file_page"
	},
	{
		"url": "https://pan.baidu.com/s/1caas5v",
		"title": "2015-07-22 151439.jpg",
		"detail": "single_file_page"
	},
	{
		"url": "https://pan.baidu.com/s/1caas5W",
		"title": "20160423192049.MTS",
		"detail": "single_file_page"
	},
	{
		"url": "https://pan.baidu.com/s/1caasgA",
		"title": "2016-08-27 140219.jpg",
		"detail": "single_file_page"
	},
	{
		"url": "https://pan.baidu.com/s/1caasgB",
		"title": "IMG_20160601_122929.jpg",
		"detail": "single_file_page"
	},
	{
		"url": "https://pan.baidu.com/s/1caasgc",
		"title": "DSC_1017.JPG",
		"detail": "single_file_page"
	},
	{
		"url": "https://pan.baidu.com/s/1caasgF",
		"title": "2016-08-02 174224.jpg",
		"detail": "single_file_page"
	},
	{
		"url": "https://pan.baidu.com/s/1caasg7",
		"title": "30 豆瓣小组推广引流",
		"detail": "multi_file"
	},
	{
		"url": "https://pan.baidu.com/s/1caasgJ",
		"title": "民法入门II物权法2.ppt",
		"detail": "single_file_page"
	},
	{
		"url": "https://pan.baidu.com/s/1caasgS",
		"title": "刘欣儿AS.zip",
		"detail": "single_file_page"
	},
	{
		"url": "https://pan.baidu.com/s/1caasgw",
		"title": "云画的月光01.rmvb",
		"detail": "single_file_page"
	},
	{
		"url": "https://pan.baidu.com/s/1caasgW",
		"title": "Full Pkg Jump 第一视角.MP4",
		"detail": "single_file_page"
	},
	{
		"url": "https://pan.baidu.com/s/1caasGc",
		"title": "2016-06-15 130313.jpg",
		"detail": "single_file_page"
	},
	{
		"url": "https://pan.baidu.com/s/1caasG4",
		"title": "Allen&amp;Peach-664.jpg",
		"detail": "single_file_page"
	},
	{
		"url": "https://pan.baidu.com/s/1caasG8",
		"title": "《平生相见即眉开》BY长干.txt",
		"detail": "single_file_page"
	},
	{
		"url": "https://pan.baidu.com/s/1caasGm",
		"title": "天正系列   精品教程",
		"detail": "multi_file"
	},
	{
		"url": "https://pan.baidu.com/s/1caasGV",
		"title": "板野友美 PV [1080P]",
		"detail": "multi_file"
	},
	{
		"url": "https://pan.baidu.com/s/1caas6A",
		"title": "我们诞生在中国.Born.in.China.2016.HD1080P.mp4",
		"detail": "single_file_page"
	},
	{
		"url": "https://pan.baidu.com/s/1caas6b",
		"title": "1.jpg",
		"detail": "single_file_page"
	},
	{
		"url": "https://pan.baidu.com/s/1caas6C",
		"title": "Transformers.Revenge.of.the.Fallen.2009.BluRay.720P.390影视.mp4",
		"detail": "single_file_page"
	},
	{
		"url": "https://pan.baidu.com/s/1caas6d",
		"title": "陶谦的鬼怪纪念册.txt",
		"detail": "single_file_page"
	},
	{
		"url": "https://pan.baidu.com/s/1caas6e",
		"title": "1457200772494.jpeg",
		"detail": "single_file_page"
	},
	{
		"url": "https://pan.baidu.com/s/1caas6F",
		"title": "高中数学必修1",
		"detail": "multi_file"
	},
	{
		"url": "https://pan.baidu.com/s/1caas66",
		"title": "IMG20150301231819.jpg",
		"detail": "single_file_page"
	},
	{
		"url": "https://pan.baidu.com/s/1caas67",
		"title": "釜山行(1)",
		"detail": "multi_file"
	},
	{
		"url": "https://pan.baidu.com/s/1caas6O",
		"title": "Farewell.My.Concubine.1993.霸王别姬.中文字幕.HR-HDTV.AC3.1024X554.x264-人人影视制作.mkv",
		"detail": "single_file_page"
	},
	{
		"url": "https://pan.baidu.com/s/1caas6R",
		"title": "2016-09-16 134247.jpg",
		"detail": "single_file_page"
	},
	{
		"url": "https://pan.baidu.com/s/1caas6x",
		"title": "4c209864hc3511a0eb451&amp;690.jpg",
		"detail": "single_file_page"
	},
	{
		"url": "https://pan.baidu.com/s/1caas6z",
		"title": "素材",
		"detail": "multi_file"
	},
	{
		"url": "https://pan.baidu.com/s/1caashA",
		"title": "鲨滩The Shallows].mp4",
		"detail": "single_file_page"
	},
	{
		"url": "https://pan.baidu.com/s/1caash0",
		"title": "QQ6.3.7巨蟹座.apk",
		"detail": "single_file_page"
	},
	{
		"url": "https://pan.baidu.com/s/1caashd",
		"title": "阿卡青花瓷 50   123.rar",
		"detail": "single_file_page"
	},
	{
		"url": "https://pan.baidu.com/s/1caashf",
		"title": "S01",
		"detail": "multi_file"
	},
	{
		"url": "https://pan.baidu.com/s/1caash6",
		"title": "dingceng0916.rar",
		"detail": "single_file_page"
	},
	{
		"url": "https://pan.baidu.com/s/1caashr",
		"title": "。.mkv",
		"detail": "single_file_page"
	},
	{
		"url": "https://pan.baidu.com/s/1caashR",
		"title": "步伐——原版德语教程系列教程 Hueber Schritte-Kursbuch.&amp;.Arbeitsbuch（1-6册）（PDF）",
		"detail": "multi_file"
	},
	{
		"url": "https://pan.baidu.com/s/1caashT",
		"title": "2016-08-05 125044.jpg",
		"detail": "single_file_page"
	},
	{
		"url": "https://pan.baidu.com/s/1caasHa",
		"title": "2014-05-31 140808.jpg",
		"detail": "single_file_page"
	},
	{
		"url": "https://pan.baidu.com/s/1caasH2",
		"title": "2015-01-06 162905.jpg",
		"detail": "multi_file"
	},
	{
		"url": "https://pan.baidu.com/s/1caasH4",
		"title": "2016-08-05 103314.jpg",
		"detail": "single_file_page"
	},
	{
		"url": "https://pan.baidu.com/s/1caasH6",
		"title": "4.zip",
		"detail": "single_file_page"
	},
	{
		"url": "https://pan.baidu.com/s/1caasHJ",
		"title": "烛光演唱会.mp4",
		"detail": "single_file_page"
	},
	{
		"url": "https://pan.baidu.com/s/1caasHq",
		"title": "CentOS.7z",
		"detail": "single_file_page"
	},
	{
		"url": "https://pan.baidu.com/s/1caasHQ",
		"title": "share(94).jpg",
		"detail": "multi_file"
	},
	{
		"url": "https://pan.baidu.com/s/1caasHr",
		"title": "语音 022.m4a",
		"detail": "single_file_page"
	},
	{
		"url": "https://pan.baidu.com/s/1caasHt",
		"title": "2016-08-22 132024.jpg",
		"detail": "single_file_page"
	},
	{
		"url": "https://pan.baidu.com/s/1caasHz",
		"title": "慢步雪谷",
		"detail": "multi_file"
	},
	{
		"url": "https://pan.baidu.com/s/1caas70",
		"title": "简约白.hwt",
		"detail": "single_file_page"
	},
	{
		"url": "https://pan.baidu.com/s/1caas7F",
		"title": "Ornamentals_3D观赏植物",
		"detail": "multi_file"
	},
	{
		"url": "https://pan.baidu.com/s/1caas75",
		"title": "解语花（中字）.mkv",
		"detail": "single_file_page"
	},
	{
		"url": "https://pan.baidu.com/s/1caas7m",
		"title": "【公基冲刺讲义】——管理、道德、公文、事业单位、经济.pdf",
		"detail": "multi_file"
	},
	{
		"url": "https://pan.baidu.com/s/1caas7o",
		"title": "1391790162911.jpeg",
		"detail": "single_file_page"
	},
	{
		"url": "https://pan.baidu.com/s/1caas7p",
		"title": "中国梦强国富强八一建军节海军航母卫星战斗机展示高清视频素材.zip",
		"detail": "single_file_page"
	},
	{
		"url": "https://pan.baidu.com/s/1caas7w",
		"title": "20141117_220004.jpg",
		"detail": "multi_file"
	},
	{
		"url": "https://pan.baidu.com/s/1caas7y",
		"title": "无补丁钢纹系统2.rar",
		"detail": "single_file_page"
	},
	{
		"url": "https://pan.baidu.com/s/1caasib",
		"title": "2016中华网校三科教学视频，大纲，讲义",
		"detail": "multi_file"
	},
	{
		"url": "https://pan.baidu.com/s/1caasi2",
		"title": "釜山行 부산행",
		"detail": "multi_file"
	},
	{
		"url": "https://pan.baidu.com/s/1caasi7",
		"title": "mmexport1463055368954.jpg",
		"detail": "single_file_page"
	},
	{
		"url": "https://pan.baidu.com/s/1caasi9",
		"title": "c-02.jpg",
		"detail": "multi_file"
	},
	{
		"url": "https://pan.baidu.com/s/1caasiO",
		"title": "2016-09-13 085944.jpg",
		"detail": "single_file_page"
	},
	{
		"url": "https://pan.baidu.com/s/1caasiP",
		"title": "2016-02-19 122206.jpg",
		"detail": "single_file_page"
	},
	{
		"url": "https://pan.baidu.com/s/1caasiW",
		"title": "mmexport1451444653956.jpg",
		"detail": "single_file_page"
	},
	{
		"url": "https://pan.baidu.com/s/1caasiX",
		"title": "大一班",
		"detail": "multi_file"
	},
	{
		"url": "https://pan.baidu.com/s/1caasIg",
		"title": "云播.apk",
		"detail": "single_file_page"
	},
	{
		"url": "https://pan.baidu.com/s/1caasIG",
		"title": "廖季文现代和声乐理影音教程",
		"detail": "multi_file"
	},
	{
		"url": "https://pan.baidu.com/s/1caasIL",
		"title": "2016-05-27 185543.jpg",
		"detail": "single_file_page"
	},
	{
		"url": "https://pan.baidu.com/s/1caasIn",
		"title": "f山行.HD1280高清韩语中字.mp4",
		"detail": "single_file_page"
	},
	{
		"url": "https://pan.baidu.com/s/1caasIo",
		"title": "2016-09-02 181304.jpg",
		"detail": "single_file_page"
	},
	{
		"url": "https://pan.baidu.com/s/1caasIx",
		"title": "2016-08-29 225650.jpg",
		"detail": "single_file_page"
	},
	{
		"url": "https://pan.baidu.com/s/1caas81",
		"title": "IMG_20150401_124347.jpg",
		"detail": "single_file_page"
	},
	{
		"url": "https://pan.baidu.com/s/1caas85",
		"title": ".2013.Bluray.720p.x264.rmvb",
		"detail": "single_file_page"
	}
]