[
	{
		"url": "https://pan.baidu.com/s/1ab3uF5",
		"title": "压缩包(53).rar",
		"detail": "single_file_page"
	},
	{
		"url": "https://pan.baidu.com/s/1ab3uF6",
		"title": "百度网盘分享",
		"detail": ""
	},
	{
		"url": "https://pan.baidu.com/s/1ab3uFz",
		"title": "2013-12-02 113947.jpg",
		"detail": "multi_file"
	},
	{
		"url": "https://pan.baidu.com/s/1ab3u5B",
		"title": "唐人叶子.txt",
		"detail": "single_file_page"
	},
	{
		"url": "https://pan.baidu.com/s/1ab3u5I",
		"title": "百度网盘分享",
		"detail": ""
	},
	{
		"url": "https://pan.baidu.com/s/1ab3ug2",
		"title": "北京检查食道癌的费用是多少.txt",
		"detail": "single_file_page"
	},
	{
		"url": "https://pan.baidu.com/s/1ab3ugf",
		"title": "荥阳哪个医院治疗妇科的技术比较好.doc",
		"detail": "single_file_page"
	},
	{
		"url": "https://pan.baidu.com/s/1ab3ugH",
		"title": "杨浦区看宫颈炎医院哪家专业 .gif",
		"detail": "single_file_page"
	},
	{
		"url": "https://pan.baidu.com/s/1ab3ugi",
		"title": "百度网盘分享",
		"detail": ""
	},
	{
		"url": "https://pan.baidu.com/s/1ab3ugm",
		"title": "Q70单摄像头",
		"detail": "multi_file"
	},
	{
		"url": "https://pan.baidu.com/s/1ab3ugR",
		"title": "百度网盘分享",
		"detail": ""
	},
	{
		"url": "https://pan.baidu.com/s/1ab3ugT",
		"title": "郑州那里治疗睾丸炎好.docx",
		"detail": "single_file_page"
	},
	{
		"url": "https://pan.baidu.com/s/1ab3ugV",
		"title": "成都金牛区治疗癲癇病.txt",
		"detail": "single_file_page"
	},
	{
		"url": "https://pan.baidu.com/s/1ab3uG5",
		"title": "百度网盘分享",
		"detail": ""
	},
	{
		"url": "https://pan.baidu.com/s/1ab3uGr",
		"title": "百度网盘分享",
		"detail": ""
	},
	{
		"url": "https://pan.baidu.com/s/1ab3uGY",
		"title": "百度网盘分享",
		"detail": ""
	},
	{
		"url": "https://pan.baidu.com/s/1ab3uhf",
		"title": "百度网盘分享",
		"detail": ""
	},
	{
		"url": "https://pan.baidu.com/s/1ab3uhj",
		"title": "百度网盘分享",
		"detail": ""
	},
	{
		"url": "https://pan.baidu.com/s/1ab3uhk",
		"title": "百度网盘分享",
		"detail": ""
	}
]